{
  "coord": {
    "lon": 0.1594,
    "lat": 52.6662
  },
  "weather": [
    {
      "id": 804,
      "main": "Clouds",
      "description": "overcast clouds",
      "icon": "04d"
    }
  ],
  "base": "stations",
  "main": {
    "temp": 10.91,
    "feels_like": 10.07,
    "temp_min": 9.46,
    "temp_max": 12.84,
    "pressure": 1026,
    "humidity": 77,
    "sea_level": 1026,
    "grnd_level": 1027
  },
  "visibility": 10000,
  "wind": {
    "speed": 8.42,
    "deg": 41,
    "gust": 10.41
  },
  "clouds": {
    "all": 85
  },
  "dt": 1777371225,
  "sys": {
    "type": 1,
    "id": 1512,
    "country": "GB",
    "sunrise": 1777350820,
    "sunset": 1777403990
  },
  "timezone": 3600,
  "id": 2633771,
  "name": "Wisbech",
  "cod": 200,
  "_last_updated_utc": "2026-04-28T10:13:45.422Z"
}