{
  "coord": {
    "lon": 0.1594,
    "lat": 52.6662
  },
  "weather": [
    {
      "id": 800,
      "main": "Clear",
      "description": "clear sky",
      "icon": "01d"
    }
  ],
  "base": "stations",
  "main": {
    "temp": 9.42,
    "feels_like": 7.34,
    "temp_min": 9,
    "temp_max": 10.06,
    "pressure": 1025,
    "humidity": 68,
    "sea_level": 1025,
    "grnd_level": 1025
  },
  "visibility": 10000,
  "wind": {
    "speed": 3.9,
    "deg": 333,
    "gust": 4.87
  },
  "clouds": {
    "all": 0
  },
  "dt": 1776588952,
  "sys": {
    "type": 1,
    "id": 1512,
    "country": "GB",
    "sunrise": 1776574357,
    "sunset": 1776625440
  },
  "timezone": 3600,
  "id": 2633771,
  "name": "Wisbech",
  "cod": 200,
  "_last_updated_utc": "2026-04-19T08:55:52.738Z"
}