{
  "coord": {
    "lon": 0.1594,
    "lat": 52.6662
  },
  "weather": [
    {
      "id": 804,
      "main": "Clouds",
      "description": "overcast clouds",
      "icon": "04n"
    }
  ],
  "base": "stations",
  "main": {
    "temp": -0.06,
    "feels_like": -0.06,
    "temp_min": -0.58,
    "temp_max": 0.57,
    "pressure": 1016,
    "humidity": 83,
    "sea_level": 1016,
    "grnd_level": 1016
  },
  "visibility": 10000,
  "wind": {
    "speed": 1.2,
    "deg": 323,
    "gust": 1.12
  },
  "clouds": {
    "all": 100
  },
  "dt": 1771360748,
  "sys": {
    "type": 1,
    "id": 1512,
    "country": "GB",
    "sunrise": 1771312349,
    "sunset": 1771348473
  },
  "timezone": 0,
  "id": 2633771,
  "name": "Wisbech",
  "cod": 200,
  "_last_updated_utc": "2026-02-17T20:39:08.938Z"
}