{
  "coord": {
    "lon": 0.1594,
    "lat": 52.6662
  },
  "weather": [
    {
      "id": 803,
      "main": "Clouds",
      "description": "broken clouds",
      "icon": "04n"
    }
  ],
  "base": "stations",
  "main": {
    "temp": 5.83,
    "feels_like": 3.29,
    "temp_min": 5,
    "temp_max": 6.68,
    "pressure": 1014,
    "humidity": 93,
    "sea_level": 1014,
    "grnd_level": 1014
  },
  "visibility": 10000,
  "wind": {
    "speed": 3.31,
    "deg": 143,
    "gust": 6.41
  },
  "clouds": {
    "all": 82
  },
  "dt": 1768804803,
  "sys": {
    "type": 1,
    "id": 1512,
    "country": "GB",
    "sunrise": 1768809575,
    "sunset": 1768839605
  },
  "timezone": 0,
  "id": 2633771,
  "name": "Wisbech",
  "cod": 200,
  "_last_updated_utc": "2026-01-19T06:40:03.529Z"
}