{
  "coord": {
    "lon": 0.1594,
    "lat": 52.6662
  },
  "weather": [
    {
      "id": 804,
      "main": "Clouds",
      "description": "overcast clouds",
      "icon": "04d"
    }
  ],
  "base": "stations",
  "main": {
    "temp": 4.94,
    "feels_like": -0.18,
    "temp_min": 4.44,
    "temp_max": 5.57,
    "pressure": 1002,
    "humidity": 74,
    "sea_level": 1002,
    "grnd_level": 1002
  },
  "visibility": 10000,
  "wind": {
    "speed": 8.89,
    "deg": 113,
    "gust": 15.22
  },
  "clouds": {
    "all": 100
  },
  "dt": 1771425904,
  "sys": {
    "type": 1,
    "id": 1512,
    "country": "GB",
    "sunrise": 1771398626,
    "sunset": 1771434988
  },
  "timezone": 0,
  "id": 2633771,
  "name": "Wisbech",
  "cod": 200,
  "_last_updated_utc": "2026-02-18T14:45:05.009Z"
}