{
  "coord": {
    "lon": 0.1594,
    "lat": 52.6662
  },
  "weather": [
    {
      "id": 803,
      "main": "Clouds",
      "description": "broken clouds",
      "icon": "04n"
    }
  ],
  "base": "stations",
  "main": {
    "temp": 4.08,
    "feels_like": -0.19,
    "temp_min": 3.89,
    "temp_max": 4.5,
    "pressure": 993,
    "humidity": 93,
    "sea_level": 993,
    "grnd_level": 993
  },
  "visibility": 10000,
  "wind": {
    "speed": 5.82,
    "deg": 248,
    "gust": 13.92
  },
  "clouds": {
    "all": 61
  },
  "dt": 1771207997,
  "sys": {
    "type": 1,
    "id": 1512,
    "country": "GB",
    "sunrise": 1771226071,
    "sunset": 1771261959
  },
  "timezone": 0,
  "id": 2633771,
  "name": "Wisbech",
  "cod": 200,
  "_last_updated_utc": "2026-02-16T02:13:17.149Z"
}