{
  "coord": {
    "lon": 0.1594,
    "lat": 52.6662
  },
  "weather": [
    {
      "id": 804,
      "main": "Clouds",
      "description": "overcast clouds",
      "icon": "04d"
    }
  ],
  "base": "stations",
  "main": {
    "temp": 16.94,
    "feels_like": 16.7,
    "temp_min": 15.62,
    "temp_max": 17.22,
    "pressure": 1011,
    "humidity": 77,
    "sea_level": 1011,
    "grnd_level": 1011
  },
  "visibility": 10000,
  "wind": {
    "speed": 4.93,
    "deg": 300,
    "gust": 6.16
  },
  "clouds": {
    "all": 85
  },
  "dt": 1780933996,
  "sys": {
    "type": 2,
    "id": 2016703,
    "country": "GB",
    "sunrise": 1780889835,
    "sunset": 1780949987
  },
  "timezone": 3600,
  "id": 2633771,
  "name": "Wisbech",
  "cod": 200,
  "_last_updated_utc": "2026-06-08T15:53:16.423Z"
}