{
  "coord": {
    "lon": 0.1594,
    "lat": 52.6662
  },
  "weather": [
    {
      "id": 804,
      "main": "Clouds",
      "description": "overcast clouds",
      "icon": "04n"
    }
  ],
  "base": "stations",
  "main": {
    "temp": 5.37,
    "feels_like": 1.62,
    "temp_min": 4.44,
    "temp_max": 7.28,
    "pressure": 1005,
    "humidity": 95,
    "sea_level": 1005,
    "grnd_level": 1005
  },
  "visibility": 10000,
  "wind": {
    "speed": 5.4,
    "deg": 169,
    "gust": 13.26
  },
  "clouds": {
    "all": 100
  },
  "dt": 1768429414,
  "sys": {
    "type": 1,
    "id": 1512,
    "country": "GB",
    "sunrise": 1768377866,
    "sunset": 1768407110
  },
  "timezone": 0,
  "id": 2633771,
  "name": "Wisbech",
  "cod": 200,
  "_last_updated_utc": "2026-01-14T22:23:34.230Z"
}